flask_rebar_auth0/__init__.py
flask_rebar_auth0/authenticator.py
flask_rebar_auth0/helpers.py
flask_rebar_auth0/swagger.py
flask_rebar_auth0-0.2.1.dist-info/LICENSE
flask_rebar_auth0-0.2.1.dist-info/METADATA
flask_rebar_auth0-0.2.1.dist-info/WHEEL
flask_rebar_auth0-0.2.1.dist-info/top_level.txt
flask_rebar_auth0-0.2.1.dist-info/RECORD
