Metadata-Version: 2.1
Name: flask-rebar-auth0
Version: 0.2.1
Summary: Flask-Rebar-Auth0 is a simple Flask-Rebar authenticator for Auth0
Home-page: https://github.com/Sytten/flask-rebar-auth0
Author: Emile Fugulin
Author-email: code@efugulin.com
License: MIT
Keywords: flask,flask-rebar,auth0
Platform: UNKNOWN
Classifier: Environment :: Web Environment
Classifier: Framework :: Flask
Classifier: Intended Audience :: Developers
Classifier: License :: OSI Approved :: MIT License
Classifier: Operating System :: OS Independent
Classifier: Programming Language :: Python
Classifier: Programming Language :: Python :: 3
Classifier: Programming Language :: Python :: 3.6
Classifier: Programming Language :: Python :: 3.7
Classifier: Programming Language :: Python :: 3.8
Classifier: Programming Language :: Python :: 3.9
Classifier: Topic :: Software Development :: Libraries
Classifier: Topic :: Utilities
Requires-Dist: flask-rebar (<2,>=1.0.0)
Requires-Dist: Flask (<2,>=0.10)
Requires-Dist: requests (<3,>=2.20.0)
Requires-Dist: python-jose (<4,>=3.0.1)
Requires-Dist: cryptography (<4,>=3.2)
Provides-Extra: dev
Requires-Dist: pytest ; extra == 'dev'
Requires-Dist: pytest-cov ; extra == 'dev'
Requires-Dist: pytest-mock ; extra == 'dev'
Requires-Dist: requests-mock ; extra == 'dev'
Requires-Dist: black ; extra == 'dev'
Requires-Dist: codecov ; extra == 'dev'
